eunomia_sdk/__init__.py
eunomia_sdk/client.py
eunomia_sdk-0.3.10.dist-info/METADATA
eunomia_sdk-0.3.10.dist-info/WHEEL
eunomia_sdk-0.3.10.dist-info/RECORD
