Metadata-Version: 2.4
Name: eunomia-sdk
Version: 0.3.10
Summary: Eunomia SDK for Python
Author-email: What About You team <info@whataboutyou.ai>
License-Expression: Apache-2.0
Requires-Python: >=3.10
Requires-Dist: eunomia-core>=0.3.10
Requires-Dist: httpx>=0.28.1
